{
 "jarCode": "300642933",
 "sodraCode": 779157,
 "name": "UAB INSPIRED COMMUNICATIONS",
 "ecoActName": "Reklamos agentūrų veikla",
 "municipality": "Vilniaus m. sav.",
 "latest": {
  "month": 202604,
  "avgWage": 4902.32,
  "numInsured": 27
 },
 "months": [
  {
   "month": 201701,
   "avgWage": 1511.68,
   "numInsured": 45,
   "tax": 27931.93
  },
  {
   "month": 201702,
   "avgWage": 1645.37,
   "numInsured": 45,
   "tax": 30400.41
  },
  {
   "month": 201703,
   "avgWage": 1624.0,
   "numInsured": 48,
   "tax": 32031.08
  },
  {
   "month": 201704,
   "avgWage": 1610.93,
   "numInsured": 47,
   "tax": 31056.57
  },
  {
   "month": 201705,
   "avgWage": 1610.69,
   "numInsured": 48,
   "tax": 31725.17
  },
  {
   "month": 201706,
   "avgWage": 1577.84,
   "numInsured": 49,
   "tax": 31699.23
  },
  {
   "month": 201707,
   "avgWage": 1652.09,
   "numInsured": 52,
   "tax": 35239.14
  },
  {
   "month": 201708,
   "avgWage": 1653.38,
   "numInsured": 52,
   "tax": 35229.43
  },
  {
   "month": 201709,
   "avgWage": 1675.49,
   "numInsured": 50,
   "tax": 34343.96
  },
  {
   "month": 201710,
   "avgWage": 1696.39,
   "numInsured": 53,
   "tax": 36948.93
  },
  {
   "month": 201711,
   "avgWage": 1681.76,
   "numInsured": 54,
   "tax": 37238.79
  },
  {
   "month": 201712,
   "avgWage": 1655.03,
   "numInsured": 54,
   "tax": 36695.29
  },
  {
   "month": 201801,
   "avgWage": 1723.89,
   "numInsured": 54,
   "tax": 38241.55
  },
  {
   "month": 201802,
   "avgWage": 1694.83,
   "numInsured": 41,
   "tax": 28486.04
  },
  {
   "month": 201803,
   "avgWage": 1790.82,
   "numInsured": 41,
   "tax": 30081.1
  },
  {
   "month": 201804,
   "avgWage": 1620.08,
   "numInsured": 40,
   "tax": 26543.6
  },
  {
   "month": 201805,
   "avgWage": 1797.87,
   "numInsured": 42,
   "tax": 30935.8
  },
  {
   "month": 201806,
   "avgWage": 1743.12,
   "numInsured": 42,
   "tax": 29972.92
  },
  {
   "month": 201807,
   "avgWage": 1730.67,
   "numInsured": 41,
   "tax": 29034.13
  },
  {
   "month": 201808,
   "avgWage": 1733.52,
   "numInsured": 44,
   "tax": 31213.65
  },
  {
   "month": 201809,
   "avgWage": 1678.47,
   "numInsured": 45,
   "tax": 30900.1
  },
  {
   "month": 201810,
   "avgWage": 1641.76,
   "numInsured": 48,
   "tax": 32252.69
  },
  {
   "month": 201811,
   "avgWage": 1738.51,
   "numInsured": 45,
   "tax": 31991.43
  },
  {
   "month": 201812,
   "avgWage": 1727.26,
   "numInsured": 45,
   "tax": 31803.87
  },
  {
   "month": 201901,
   "avgWage": 2248.72,
   "numInsured": 43,
   "tax": 22370.87
  },
  {
   "month": 201902,
   "avgWage": 2237.46,
   "numInsured": 44,
   "tax": 22693.74
  },
  {
   "month": 201903,
   "avgWage": 2272.06,
   "numInsured": 45,
   "tax": 23464.05
  },
  {
   "month": 201904,
   "avgWage": 2397.17,
   "numInsured": 46,
   "tax": 25328.51
  },
  {
   "month": 201905,
   "avgWage": 2311.97,
   "numInsured": 47,
   "tax": 24971.16
  },
  {
   "month": 201906,
   "avgWage": 2714.22,
   "numInsured": 50,
   "tax": 31071.18
  },
  {
   "month": 201907,
   "avgWage": 2237.42,
   "numInsured": 48,
   "tax": 24605.5
  },
  {
   "month": 201908,
   "avgWage": 2385.89,
   "numInsured": 48,
   "tax": 26311.28
  },
  {
   "month": 201909,
   "avgWage": 3087.23,
   "numInsured": 50,
   "tax": 35609.23
  },
  {
   "month": 201910,
   "avgWage": 2254.08,
   "numInsured": 46,
   "tax": 23740.7
  },
  {
   "month": 201911,
   "avgWage": 2347.1,
   "numInsured": 45,
   "tax": 24169.67
  },
  {
   "month": 201912,
   "avgWage": 2392.89,
   "numInsured": 45,
   "tax": 24655.03
  },
  {
   "month": 202001,
   "avgWage": 2370.47,
   "numInsured": 46,
   "tax": 25078.57
  },
  {
   "month": 202002,
   "avgWage": 2466.1,
   "numInsured": 45,
   "tax": 25468.46
  },
  {
   "month": 202003,
   "avgWage": 1969.27,
   "numInsured": 45,
   "tax": 20404.18
  },
  {
   "month": 202004,
   "avgWage": 1660.69,
   "numInsured": 35,
   "tax": 13391.03
  },
  {
   "month": 202005,
   "avgWage": 1642.9,
   "numInsured": 39,
   "tax": 14718.1
  },
  {
   "month": 202006,
   "avgWage": 2071.08,
   "numInsured": 41,
   "tax": 19597.3
  },
  {
   "month": 202007,
   "avgWage": 2128.2,
   "numInsured": 41,
   "tax": 20059.27
  },
  {
   "month": 202008,
   "avgWage": 2316.43,
   "numInsured": 42,
   "tax": 22351.72
  },
  {
   "month": 202009,
   "avgWage": 2429.58,
   "numInsured": 42,
   "tax": 23273.18
  },
  {
   "month": 202010,
   "avgWage": 2498.08,
   "numInsured": 45,
   "tax": 25617.06
  },
  {
   "month": 202011,
   "avgWage": 2387.23,
   "numInsured": 46,
   "tax": 25147.34
  },
  {
   "month": 202012,
   "avgWage": 2454.91,
   "numInsured": 46,
   "tax": 25853.55
  },
  {
   "month": 202101,
   "avgWage": 2379.73,
   "numInsured": 47,
   "tax": 25710.1
  },
  {
   "month": 202102,
   "avgWage": 2461.39,
   "numInsured": 47,
   "tax": 26671.19
  },
  {
   "month": 202103,
   "avgWage": 2438.05,
   "numInsured": 46,
   "tax": 25818.71
  },
  {
   "month": 202104,
   "avgWage": 2389.48,
   "numInsured": 48,
   "tax": 26443.8
  },
  {
   "month": 202105,
   "avgWage": 2442.37,
   "numInsured": 51,
   "tax": 28627.71
  },
  {
   "month": 202106,
   "avgWage": 2617.86,
   "numInsured": 49,
   "tax": 29462.25
  },
  {
   "month": 202107,
   "avgWage": 2486.26,
   "numInsured": 46,
   "tax": 26342.49
  },
  {
   "month": 202108,
   "avgWage": 2504.35,
   "numInsured": 48,
   "tax": 27668.53
  },
  {
   "month": 202109,
   "avgWage": 2431.8,
   "numInsured": 49,
   "tax": 27467.38
  },
  {
   "month": 202110,
   "avgWage": 2465.27,
   "numInsured": 49,
   "tax": 27863.6
  },
  {
   "month": 202111,
   "avgWage": 2493.41,
   "numInsured": 49,
   "tax": 28265.38
  },
  {
   "month": 202112,
   "avgWage": 2882.95,
   "numInsured": 48,
   "tax": 31367.67
  },
  {
   "month": 202201,
   "avgWage": 2417.33,
   "numInsured": 48,
   "tax": 26867.78
  },
  {
   "month": 202202,
   "avgWage": 2473.7,
   "numInsured": 49,
   "tax": 27957.11
  },
  {
   "month": 202203,
   "avgWage": 2825.77,
   "numInsured": 46,
   "tax": 29873.26
  },
  {
   "month": 202204,
   "avgWage": 2839.42,
   "numInsured": 38,
   "tax": 24925.72
  },
  {
   "month": 202205,
   "avgWage": 3047.96,
   "numInsured": 34,
   "tax": 23905.13
  },
  {
   "month": 202206,
   "avgWage": 3014.48,
   "numInsured": 32,
   "tax": 22206.48
  },
  {
   "month": 202207,
   "avgWage": 2990.16,
   "numInsured": 32,
   "tax": 22159.3
  },
  {
   "month": 202208,
   "avgWage": 3107.96,
   "numInsured": 32,
   "tax": 23229.87
  },
  {
   "month": 202209,
   "avgWage": 2781.17,
   "numInsured": 35,
   "tax": 22810.43
  },
  {
   "month": 202210,
   "avgWage": 2909.45,
   "numInsured": 36,
   "tax": 24652.19
  },
  {
   "month": 202211,
   "avgWage": 2968.08,
   "numInsured": 35,
   "tax": 24430.57
  },
  {
   "month": 202212,
   "avgWage": 3390.48,
   "numInsured": 34,
   "tax": 27167.97
  },
  {
   "month": 202301,
   "avgWage": 3155.57,
   "numInsured": 30,
   "tax": 22425.28
  },
  {
   "month": 202302,
   "avgWage": 3209.32,
   "numInsured": 32,
   "tax": 24362.33
  },
  {
   "month": 202303,
   "avgWage": 3820.34,
   "numInsured": 29,
   "tax": 26134.77
  },
  {
   "month": 202304,
   "avgWage": 3408.79,
   "numInsured": 30,
   "tax": 24136.09
  },
  {
   "month": 202305,
   "avgWage": 3554.6,
   "numInsured": 30,
   "tax": 25182.2
  },
  {
   "month": 202306,
   "avgWage": 3698.55,
   "numInsured": 31,
   "tax": 27126.17
  },
  {
   "month": 202307,
   "avgWage": 3597.64,
   "numInsured": 31,
   "tax": 26305.67
  },
  {
   "month": 202308,
   "avgWage": 3574.75,
   "numInsured": 32,
   "tax": 26958.89
  },
  {
   "month": 202309,
   "avgWage": 3582.36,
   "numInsured": 32,
   "tax": 26988.67
  },
  {
   "month": 202310,
   "avgWage": 3657.04,
   "numInsured": 31,
   "tax": 26799.41
  },
  {
   "month": 202311,
   "avgWage": 3629.21,
   "numInsured": 31,
   "tax": 26632.13
  },
  {
   "month": 202312,
   "avgWage": 4461.63,
   "numInsured": 30,
   "tax": 30562.33
  },
  {
   "month": 202401,
   "avgWage": 3800.42,
   "numInsured": 30,
   "tax": 27006.84
  },
  {
   "month": 202402,
   "avgWage": 3750.0,
   "numInsured": 30,
   "tax": 26641.24
  },
  {
   "month": 202403,
   "avgWage": 7296.55,
   "numInsured": 30,
   "tax": 51461.39
  },
  {
   "month": 202404,
   "avgWage": 4146.72,
   "numInsured": 29,
   "tax": 28250.01
  },
  {
   "month": 202405,
   "avgWage": 4109.95,
   "numInsured": 29,
   "tax": 28240.84
  },
  {
   "month": 202406,
   "avgWage": 3890.63,
   "numInsured": 31,
   "tax": 28629.96
  },
  {
   "month": 202407,
   "avgWage": 3859.43,
   "numInsured": 31,
   "tax": 28418.93
  },
  {
   "month": 202408,
   "avgWage": 3934.19,
   "numInsured": 29,
   "tax": 27072.99
  },
  {
   "month": 202409,
   "avgWage": 3826.7,
   "numInsured": 32,
   "tax": 29054.22
  },
  {
   "month": 202410,
   "avgWage": 3602.06,
   "numInsured": 33,
   "tax": 28095.72
  },
  {
   "month": 202411,
   "avgWage": 3805.89,
   "numInsured": 30,
   "tax": 27066.38
  },
  {
   "month": 202412,
   "avgWage": 4415.46,
   "numInsured": 29,
   "tax": 29167.38
  },
  {
   "month": 202501,
   "avgWage": 3810.83,
   "numInsured": 29,
   "tax": 26269.04
  },
  {
   "month": 202502,
   "avgWage": 4809.08,
   "numInsured": 31,
   "tax": 35200.06
  },
  {
   "month": 202503,
   "avgWage": 4008.85,
   "numInsured": 29,
   "tax": 27693.39
  },
  {
   "month": 202504,
   "avgWage": 4231.34,
   "numInsured": 28,
   "tax": 28225.38
  },
  {
   "month": 202505,
   "avgWage": 4210.77,
   "numInsured": 28,
   "tax": 28106.31
  },
  {
   "month": 202506,
   "avgWage": 4208.53,
   "numInsured": 27,
   "tax": 27080.04
  },
  {
   "month": 202507,
   "avgWage": 4329.84,
   "numInsured": 28,
   "tax": 28930.88
  },
  {
   "month": 202508,
   "avgWage": 4277.84,
   "numInsured": 27,
   "tax": 27609.78
  },
  {
   "month": 202509,
   "avgWage": 4331.75,
   "numInsured": 27,
   "tax": 27969.89
  },
  {
   "month": 202510,
   "avgWage": 4414.71,
   "numInsured": 27,
   "tax": 28495.61
  },
  {
   "month": 202511,
   "avgWage": 4645.28,
   "numInsured": 26,
   "tax": 28892.98
  },
  {
   "month": 202512,
   "avgWage": 4501.44,
   "numInsured": 25,
   "tax": 26895.78
  },
  {
   "month": 202601,
   "avgWage": 4550.47,
   "numInsured": 27,
   "tax": 29331.56
  },
  {
   "month": 202602,
   "avgWage": 4233.82,
   "numInsured": 26,
   "tax": 26232.71
  },
  {
   "month": 202603,
   "avgWage": 6203.21,
   "numInsured": 28,
   "tax": 40492.23
  },
  {
   "month": 202604,
   "avgWage": 4902.32,
   "numInsured": 27,
   "tax": 30783.81
  }
 ],
 "source": "atvira.sodra.lt (open data)"
}