{
 "jarCode": "301732159",
 "sodraCode": 1003380,
 "name": "UAB \"DANSU\"",
 "ecoActName": "Reklamos agentūrų veikla",
 "municipality": "Vilniaus m. sav.",
 "latest": {
  "month": 202604,
  "avgWage": 2170.76,
  "numInsured": 5
 },
 "months": [
  {
   "month": 201701,
   "avgWage": 1170.88,
   "numInsured": 6,
   "tax": 2935.32
  },
  {
   "month": 201702,
   "avgWage": 1225.28,
   "numInsured": 6,
   "tax": 3065.59
  },
  {
   "month": 201703,
   "avgWage": 1248.11,
   "numInsured": 6,
   "tax": 3123.38
  },
  {
   "month": 201704,
   "avgWage": 816.93,
   "numInsured": 6,
   "tax": 2051.77
  },
  {
   "month": 201705,
   "avgWage": 1193.03,
   "numInsured": 6,
   "tax": 2987.23
  },
  {
   "month": 201706,
   "avgWage": 1250.03,
   "numInsured": 6,
   "tax": 3139.32
  },
  {
   "month": 201707,
   "avgWage": 1227.91,
   "numInsured": 6,
   "tax": 3085.78
  },
  {
   "month": 201708,
   "avgWage": 1193.02,
   "numInsured": 6,
   "tax": 3001.67
  },
  {
   "month": 201709,
   "avgWage": 1121.18,
   "numInsured": 7,
   "tax": 3278.95
  },
  {
   "month": 201710,
   "avgWage": 1127.72,
   "numInsured": 7,
   "tax": 3297.83
  },
  {
   "month": 201711,
   "avgWage": 1118.68,
   "numInsured": 7,
   "tax": 3271.3
  },
  {
   "month": 201712,
   "avgWage": 1117.54,
   "numInsured": 7,
   "tax": 3267.76
  },
  {
   "month": 201801,
   "avgWage": 1093.31,
   "numInsured": 7,
   "tax": 3200.63
  },
  {
   "month": 201802,
   "avgWage": 1084.87,
   "numInsured": 7,
   "tax": 3176.42
  },
  {
   "month": 201803,
   "avgWage": 1226.97,
   "numInsured": 7,
   "tax": 3590.86
  },
  {
   "month": 201804,
   "avgWage": 1230.67,
   "numInsured": 7,
   "tax": 3601.79
  },
  {
   "month": 201805,
   "avgWage": 1810.1,
   "numInsured": 7,
   "tax": 5299.11
  },
  {
   "month": 201806,
   "avgWage": 1230.67,
   "numInsured": 7,
   "tax": 3601.79
  },
  {
   "month": 201807,
   "avgWage": 1240.67,
   "numInsured": 7,
   "tax": 3631.32
  },
  {
   "month": 201808,
   "avgWage": 1245.39,
   "numInsured": 7,
   "tax": 3643.21
  },
  {
   "month": 201809,
   "avgWage": 1229.3,
   "numInsured": 7,
   "tax": 3598.96
  },
  {
   "month": 201810,
   "avgWage": 1208.05,
   "numInsured": 7,
   "tax": 3536.56
  },
  {
   "month": 201811,
   "avgWage": 1084.51,
   "numInsured": 7,
   "tax": 3175.81
  },
  {
   "month": 201812,
   "avgWage": 1403.33,
   "numInsured": 7,
   "tax": 4110.81
  },
  {
   "month": 201901,
   "avgWage": 1469.03,
   "numInsured": 7,
   "tax": 2471.34
  },
  {
   "month": 201902,
   "avgWage": 1410.6,
   "numInsured": 7,
   "tax": 2372.73
  },
  {
   "month": 201903,
   "avgWage": 1549.14,
   "numInsured": 7,
   "tax": 2607.23
  },
  {
   "month": 201904,
   "avgWage": 1602.66,
   "numInsured": 6,
   "tax": 2315.3
  },
  {
   "month": 201905,
   "avgWage": 1927.4,
   "numInsured": 5,
   "tax": 2320.18
  },
  {
   "month": 201906,
   "avgWage": 1927.4,
   "numInsured": 5,
   "tax": 2320.18
  },
  {
   "month": 201907,
   "avgWage": 1927.4,
   "numInsured": 5,
   "tax": 2320.18
  },
  {
   "month": 201908,
   "avgWage": 1927.4,
   "numInsured": 5,
   "tax": 2320.18
  },
  {
   "month": 201909,
   "avgWage": 2077.4,
   "numInsured": 5,
   "tax": 2502.21
  },
  {
   "month": 201910,
   "avgWage": 2085.61,
   "numInsured": 5,
   "tax": 2512.02
  },
  {
   "month": 201911,
   "avgWage": 2051.51,
   "numInsured": 5,
   "tax": 2470.8
  },
  {
   "month": 201912,
   "avgWage": 2058.19,
   "numInsured": 5,
   "tax": 2480.05
  },
  {
   "month": 202001,
   "avgWage": 1834.81,
   "numInsured": 5,
   "tax": 2212.34
  },
  {
   "month": 202002,
   "avgWage": 1882.38,
   "numInsured": 5,
   "tax": 2270.23
  },
  {
   "month": 202003,
   "avgWage": 1787.4,
   "numInsured": 5,
   "tax": 2154.97
  },
  {
   "month": 202004,
   "avgWage": 1787.47,
   "numInsured": 5,
   "tax": 2155.02
  },
  {
   "month": 202005,
   "avgWage": 1929.4,
   "numInsured": 5,
   "tax": 2326.0
  },
  {
   "month": 202006,
   "avgWage": 1968.27,
   "numInsured": 5,
   "tax": 2374.44
  },
  {
   "month": 202007,
   "avgWage": 1967.4,
   "numInsured": 5,
   "tax": 2373.4
  },
  {
   "month": 202008,
   "avgWage": 1967.4,
   "numInsured": 5,
   "tax": 2373.4
  },
  {
   "month": 202009,
   "avgWage": 1967.4,
   "numInsured": 5,
   "tax": 2373.4
  },
  {
   "month": 202010,
   "avgWage": 1967.4,
   "numInsured": 5,
   "tax": 2373.4
  },
  {
   "month": 202011,
   "avgWage": 1967.4,
   "numInsured": 5,
   "tax": 2373.4
  },
  {
   "month": 202012,
   "avgWage": 2522.46,
   "numInsured": 5,
   "tax": 3046.97
  },
  {
   "month": 202101,
   "avgWage": 1976.53,
   "numInsured": 5,
   "tax": 2389.17
  },
  {
   "month": 202102,
   "avgWage": 1837.29,
   "numInsured": 5,
   "tax": 2220.21
  },
  {
   "month": 202103,
   "avgWage": 1855.04,
   "numInsured": 5,
   "tax": 2241.75
  },
  {
   "month": 202104,
   "avgWage": 1967.4,
   "numInsured": 5,
   "tax": 2378.09
  },
  {
   "month": 202105,
   "avgWage": 2055.4,
   "numInsured": 5,
   "tax": 2484.88
  },
  {
   "month": 202106,
   "avgWage": 2020.37,
   "numInsured": 5,
   "tax": 2442.37
  },
  {
   "month": 202107,
   "avgWage": 1732.16,
   "numInsured": 5,
   "tax": 2092.62
  },
  {
   "month": 202108,
   "avgWage": 2077.4,
   "numInsured": 5,
   "tax": 2511.58
  },
  {
   "month": 202109,
   "avgWage": 2077.4,
   "numInsured": 5,
   "tax": 2511.58
  },
  {
   "month": 202110,
   "avgWage": 2100.08,
   "numInsured": 5,
   "tax": 2539.1
  },
  {
   "month": 202111,
   "avgWage": 2100.08,
   "numInsured": 5,
   "tax": 2539.1
  },
  {
   "month": 202112,
   "avgWage": 2101.21,
   "numInsured": 5,
   "tax": 2540.47
  },
  {
   "month": 202201,
   "avgWage": 1766.28,
   "numInsured": 5,
   "tax": 2138.7
  },
  {
   "month": 202202,
   "avgWage": 2018.05,
   "numInsured": 5,
   "tax": 2444.23
  },
  {
   "month": 202203,
   "avgWage": 2053.02,
   "numInsured": 5,
   "tax": 2486.66
  },
  {
   "month": 202204,
   "avgWage": 2100.47,
   "numInsured": 5,
   "tax": 2544.25
  },
  {
   "month": 202205,
   "avgWage": 2100.47,
   "numInsured": 5,
   "tax": 2544.25
  },
  {
   "month": 202206,
   "avgWage": 2098.53,
   "numInsured": 5,
   "tax": 2541.9
  },
  {
   "month": 202207,
   "avgWage": 2091.77,
   "numInsured": 5,
   "tax": 2533.7
  },
  {
   "month": 202208,
   "avgWage": 1817.23,
   "numInsured": 5,
   "tax": 2200.44
  },
  {
   "month": 202209,
   "avgWage": 2170.47,
   "numInsured": 5,
   "tax": 2629.19
  },
  {
   "month": 202210,
   "avgWage": 2170.47,
   "numInsured": 5,
   "tax": 2629.19
  },
  {
   "month": 202211,
   "avgWage": 2170.47,
   "numInsured": 5,
   "tax": 2629.19
  },
  {
   "month": 202212,
   "avgWage": 2169.87,
   "numInsured": 5,
   "tax": 2628.47
  },
  {
   "month": 202301,
   "avgWage": 1862.02,
   "numInsured": 5,
   "tax": 2259.57
  },
  {
   "month": 202302,
   "avgWage": 2176.5,
   "numInsured": 5,
   "tax": 2641.2
  },
  {
   "month": 202303,
   "avgWage": 2176.5,
   "numInsured": 5,
   "tax": 2641.2
  },
  {
   "month": 202304,
   "avgWage": 2176.5,
   "numInsured": 5,
   "tax": 2641.2
  },
  {
   "month": 202305,
   "avgWage": 2196.35,
   "numInsured": 5,
   "tax": 2665.29
  },
  {
   "month": 202306,
   "avgWage": 2176.5,
   "numInsured": 5,
   "tax": 2641.2
  },
  {
   "month": 202307,
   "avgWage": 2126.97,
   "numInsured": 5,
   "tax": 2581.08
  },
  {
   "month": 202308,
   "avgWage": 2101.57,
   "numInsured": 5,
   "tax": 2550.27
  },
  {
   "month": 202309,
   "avgWage": 2176.5,
   "numInsured": 5,
   "tax": 2641.2
  },
  {
   "month": 202310,
   "avgWage": 2176.5,
   "numInsured": 5,
   "tax": 2641.2
  },
  {
   "month": 202311,
   "avgWage": 2165.93,
   "numInsured": 5,
   "tax": 2628.37
  },
  {
   "month": 202312,
   "avgWage": 2154.23,
   "numInsured": 5,
   "tax": 2614.18
  },
  {
   "month": 202401,
   "avgWage": 2197.41,
   "numInsured": 5,
   "tax": 2666.58
  },
  {
   "month": 202402,
   "avgWage": 2177.31,
   "numInsured": 5,
   "tax": 2642.19
  },
  {
   "month": 202403,
   "avgWage": 2177.31,
   "numInsured": 5,
   "tax": 2642.19
  },
  {
   "month": 202404,
   "avgWage": 2177.31,
   "numInsured": 5,
   "tax": 2642.19
  },
  {
   "month": 202405,
   "avgWage": 2189.22,
   "numInsured": 5,
   "tax": 2656.65
  },
  {
   "month": 202406,
   "avgWage": 2164.26,
   "numInsured": 5,
   "tax": 2626.36
  },
  {
   "month": 202407,
   "avgWage": 1823.31,
   "numInsured": 5,
   "tax": 2212.61
  },
  {
   "month": 202408,
   "avgWage": 2177.31,
   "numInsured": 5,
   "tax": 2642.19
  },
  {
   "month": 202409,
   "avgWage": 2177.31,
   "numInsured": 5,
   "tax": 2642.19
  },
  {
   "month": 202410,
   "avgWage": 2177.31,
   "numInsured": 5,
   "tax": 2642.19
  },
  {
   "month": 202411,
   "avgWage": 2577.31,
   "numInsured": 5,
   "tax": 3127.59
  },
  {
   "month": 202412,
   "avgWage": 2177.31,
   "numInsured": 5,
   "tax": 2642.19
  },
  {
   "month": 202501,
   "avgWage": 2392.51,
   "numInsured": 5,
   "tax": 2903.33
  },
  {
   "month": 202502,
   "avgWage": 2354.87,
   "numInsured": 5,
   "tax": 2857.65
  },
  {
   "month": 202503,
   "avgWage": 2437.9,
   "numInsured": 5,
   "tax": 2958.41
  },
  {
   "month": 202504,
   "avgWage": 2461.51,
   "numInsured": 5,
   "tax": 2987.07
  },
  {
   "month": 202505,
   "avgWage": 2461.51,
   "numInsured": 5,
   "tax": 2987.07
  },
  {
   "month": 202506,
   "avgWage": 2007.11,
   "numInsured": 5,
   "tax": 2435.64
  },
  {
   "month": 202507,
   "avgWage": 2017.53,
   "numInsured": 5,
   "tax": 2448.28
  },
  {
   "month": 202508,
   "avgWage": 1988.63,
   "numInsured": 5,
   "tax": 2413.23
  },
  {
   "month": 202509,
   "avgWage": 2021.26,
   "numInsured": 5,
   "tax": 2452.81
  },
  {
   "month": 202510,
   "avgWage": 2022.49,
   "numInsured": 5,
   "tax": 2454.31
  },
  {
   "month": 202511,
   "avgWage": 2170.11,
   "numInsured": 5,
   "tax": 2633.45
  },
  {
   "month": 202512,
   "avgWage": 2170.11,
   "numInsured": 5,
   "tax": 2633.45
  },
  {
   "month": 202601,
   "avgWage": 2165.6,
   "numInsured": 5,
   "tax": 2627.97
  },
  {
   "month": 202602,
   "avgWage": 2165.6,
   "numInsured": 5,
   "tax": 2627.97
  },
  {
   "month": 202603,
   "avgWage": 2165.6,
   "numInsured": 5,
   "tax": 2627.97
  },
  {
   "month": 202604,
   "avgWage": 2170.76,
   "numInsured": 5,
   "tax": 2634.23
  }
 ],
 "source": "atvira.sodra.lt (open data)"
}